setup.py
approxeng.task.egg-info/PKG-INFO
approxeng.task.egg-info/SOURCES.txt
approxeng.task.egg-info/dependency_links.txt
approxeng.task.egg-info/not-zip-safe
approxeng.task.egg-info/requires.txt
approxeng.task.egg-info/top_level.txt
approxeng/task/__init__.py
approxeng/task/menu.py